bk_return_sales/__init__.py
bk_return_sales/bk_main.py
bk_return_sales-0.1.4.dist-info/METADATA
bk_return_sales-0.1.4.dist-info/WHEEL
bk_return_sales-0.1.4.dist-info/entry_points.txt
bk_return_sales-0.1.4.dist-info/top_level.txt
bk_return_sales-0.1.4.dist-info/RECORD
